{
  "resourceType": "List",
  "id": "ema3868575536701",
  "text": {
    "status": "generated",
    "div": "<div xmlns=\"http://www.w3.org/1999/xhtml\"><table class=\"clstu\"><tr><td>Mode: workingStatus: current</td></tr><tr><td></td></tr></table><table class=\"grid\"><tr style=\"backgound-color: #eeeeee\"><td><b>Items</b></td></tr><tr><td><a href=\"MedicinalProductDefinition-emacfsb1639760186202.html\">MedicinalProductDefinition/emacfsb1639760186202</a></td></tr></table></div>"
  },
  "status": "current",
  "mode": "working",
  "entry": [
    {
      "item": {
        "reference": "MedicinalProductDefinition/emacfsb1639760186202"
      }
    }
  ]
}